{
  "model_info": {
    "total_records": 201,
    "original_records": 209,
    "dropped_records": 8,
    "game_mode": "RehaFlow",
    "difficulty": -1,
    "duration_minutes": 10.0
  },
  "training_date": "2025-07-14T15:47:02.832426",
  "features": [
    "score",
    "age",
    "startSpeed",
    "duration_minutes"
  ],
  "n_clusters": 4,
  "cluster_stats": {
    "count": {
      "0": 34,
      "1": 60,
      "2": 96,
      "3": 11
    },
    "score_mean": {
      "0": 211560.53,
      "1": 172554.82,
      "2": 198203.29,
      "3": 208834.91
    },
    "score_std": {
      "0": 13244.34,
      "1": 73226.98,
      "2": 39468.81,
      "3": 140975.82
    },
    "score_min": {
      "0": 180772,
      "1": 300,
      "2": 39208,
      "3": 2150
    },
    "score_max": {
      "0": 235550,
      "1": 314890,
      "2": 260887,
      "3": 348917
    },
    "avg_age": {
      "0": 62.72,
      "1": 42.31,
      "2": 65.05,
      "3": 33.5
    },
    "avg_start_speed": {
      "0": 5.41,
      "1": 4.15,
      "2": 4.62,
      "3": 8.0
    },
    "avg_confidence": {
      "0": 1.0,
      "1": 1.0,
      "2": 1.0,
      "3": 1.0
    }
  },
  "percentile_targets": {
    "0": {
      "5th": 185531,
      "10th": 196584,
      "15th": 198645,
      "20th": 204708,
      "25th": 206887,
      "30th": 207945,
      "35th": 208158,
      "40th": 209380,
      "45th": 210137,
      "50th": 210525,
      "55th": 211545,
      "60th": 213130,
      "65th": 215495,
      "70th": 216990,
      "75th": 219612,
      "80th": 223020,
      "85th": 225599,
      "90th": 228750,
      "95th": 231742
    },
    "1": {
      "5th": 6777,
      "10th": 50321,
      "15th": 89183,
      "20th": 135720,
      "25th": 162225,
      "30th": 171623,
      "35th": 177305,
      "40th": 181580,
      "45th": 189940,
      "50th": 193875,
      "55th": 196680,
      "60th": 200340,
      "65th": 207712,
      "70th": 214870,
      "75th": 217225,
      "80th": 218560,
      "85th": 227150,
      "90th": 236341,
      "95th": 253174
    },
    "2": {
      "5th": 119600,
      "10th": 146938,
      "15th": 169241,
      "20th": 182455,
      "25th": 187178,
      "30th": 189775,
      "35th": 195641,
      "40th": 201496,
      "45th": 203813,
      "50th": 206339,
      "55th": 209267,
      "60th": 213284,
      "65th": 218347,
      "70th": 220631,
      "75th": 223339,
      "80th": 226790,
      "85th": 228809,
      "90th": 233398,
      "95th": 240924
    },
    "3": {
      "5th": 2600,
      "10th": 3050,
      "15th": 12845,
      "20th": 22640,
      "25th": 91380,
      "30th": 160120,
      "35th": 177660,
      "40th": 195200,
      "45th": 231924,
      "50th": 268649,
      "55th": 292399,
      "60th": 316150,
      "65th": 320594,
      "70th": 325038,
      "75th": 326019,
      "80th": 327000,
      "85th": 327635,
      "90th": 328270,
      "95th": 338593
    }
  }
}